{"cameraMode":{"drawMode":0,"name":"Shaded","section":"Shading Mode"},"sceneLighting":true,"audioPlay":false,"sceneViewState":{"m_AlwaysRefresh":false,"showFog":true,"showSkybox":true,"showFlares":true,"showImageEffects":true,"showParticleSystems":true,"showVisualEffectGraphs":true,"m_FxEnabled":true},"in2DMode":false,"pivot":{"x":1741.061767578125,"y":73.34588623046875,"z":0.0},"rotation":{"x":-0.04227737709879875,"y":0.030564894899725915,"z":-0.0012939909938722849,"w":-0.9986379146575928},"size":162.94204711914063,"orthographic":false}